{
  "name": "Lumino Midnight",

  "colors": {
    "activityBar.background": "#11111b",
    "activityBar.foreground": "#89b4fa",
    "activityBar.inactiveForeground": "#ffffff66",
    "activityBarBadge.background": "#89b4fa",
    "activityBarBadge.foreground": "#181825",

    "badge.background": "#89b4fa",
    "badge.foreground": "#181825",

    "dropdown.background": "#181825",
    "dropdown.border": "#181825",

    "editor.background": "#1e1e2e",
    "editor.foreground": "#cdd6f4",
    "editor.selectionBackground": "#585b70",
    "editor.selectionHighlightBackground": "#585b7066",
    "editor.wordHighlightBackground": "#585b7033",
    "editor.wordHighlightStrongBackground": "#585b7055",
    "editorBracketMatch.background": "#313244",
    "editorBracketMatch.border": "#a6adc8",
    "editorGroupHeader.tabsBackground": "#11111b",
    "editorGroup.border": "#181825",
    "editorGutter.background": "#1e1e2e",
    "editorIndentGuide.background1": "#3B3F51",
    "editorIndentGuide.activeBackground1": "#6c7086",
    "editorLineNumber.foreground": "#6c7086",
    "editorLineNumber.activeForeground": "#a6adc8",
    "editorWhitespace.foreground": "#3B3F51",

    "input.background": "#181825",
    "input.foreground": "#cdd6f4",
    "input.border": "#181825",

    "list.activeSelectionBackground": "#313244",
    "list.activeSelectionForeground": "#cdd6f4",
    "list.hoverBackground": "#2A2E3F",
    "list.inactiveSelectionBackground": "#2A2E3F",
    "list.inactiveSelectionForeground": "#cdd6f4",
    "list.highlightForeground": "#89b4fa",

    "scrollbarSlider.background": "#a6adc833",
    "scrollbarSlider.hoverBackground": "#a6adc844",
    "scrollbarSlider.activeBackground": "#a6adc866",

    "sideBar.background": "#181825",
    "sideBar.foreground": "#cdd6f4",
    "sideBarTitle.foreground": "#89b4fa",
    "sideBarSectionHeader.foreground": "#cdd6f4",
    "sideBarSectionHeader.background": "#181825",
    "sideBar.border": "#181825",

    "statusBar.background": "#11111b",
    "statusBar.foreground": "#cdd6f4",
    "statusBar.border": "#11111b",
    "statusBarItem.remoteBackground": "#89b4fa",

    "tab.activeBackground": "#1e1e2e",
    "tab.activeForeground": "#cdd6f4",
    "tab.inactiveBackground": "#181825",
    "tab.inactiveForeground": "#cdd6f4",
    "tab.border": "#1E2030",

    "titleBar.activeBackground": "#11111b",
    "titleBar.activeForeground": "#cdd6f4",
    "titleBar.inactiveBackground": "#11111b",
    "titleBar.inactiveForeground": "#a6adc8b0"
  },

  "tokenColors": [
    {
      "settings": {
        "background": "#282c34",
        "foreground": "#abb2bf",
        "findHighlight": "#FFE792",
        "findHighlightForeground": "#000000",
        "selectionBorder": "#222218",
        "activeGuide": "#9D550FB0",
        "bracketsForeground": "#F8F8F2A5",
        "bracketsOptions": "underline",
        "bracketContentsForeground": "#F8F8F2A5",
        "bracketContentsOptions": "underline",
        "tagsOptions": "stippled_underline"
      }
    },
    {
      "name": "Comment",
      "scope": "comment",
      "settings": {
        "foreground": "#5c6370",
        "fontStyle": "italic"
      }
    },
    {
      "name": "Comment",
      "scope": "html.doctype",
      "settings": {
        "foreground": "#5c6370",
        "fontStyle": "italic"
      }
    },
    {
      "name": "String",
      "scope": "string",
      "settings": {
        "foreground": "#98c379"
      }
    },
    {
      "name": "Embeded String Begin and End",
      "scope": ["string.embedded.begin", "string.embedded.end"],
      "settings": {
        "foreground": "#e06c75"
      }
    },
    {
      "name": "Embeded String",
      "scope": "string.embedded",
      "settings": {
        "foreground": "#56b6c2"
      }
    },
    {
      "name": "Number",
      "scope": "constant.numeric",
      "settings": {
        "foreground": "#d19a66"
      }
    },
    {
      "name": "Built-in constant",
      "scope": "constant.language",
      "settings": {
        "foreground": "#d19a66"
      }
    },
    {
      "name": "User-defined constant",
      "scope": ["constant.character", "constant.other"],
      "settings": {
        "foreground": "#d19a66"
      }
    },
    {
      "name": "Language Variable",
      "scope": "variable.language",
      "settings": {
        "foreground": "#c678dd"
      }
    },
    {
      "name": "Variable",
      "scope": ["variable.readwrite", "variable.block", "variable.support"],
      "settings": {
        "foreground": "#e06c75"
      }
    },
    {
      "name": "Variable",
      "scope": "variable.readwrite.var-single-variable.js",
      "settings": {
        "foreground": "#d19a66"
      }
    },
    {
      "name": "Variable",
      "scope": "variable.readwrite.js",
      "settings": {
        "foreground": "#abb2bf"
      }
    },
    {
      "name": "Keyword",
      "scope": [
        "keyword",
        "keyword.operator.logical",
        "keyword.operator.constructor",
        "keyword.operator.new"
      ],
      "settings": {
        "foreground": "#c678dd"
      }
    },
    {
      "name": "Keyword Operator",
      "scope": "keyword.operator",
      "settings": {
        "foreground": "#61afef"
      }
    },
    {
      "name": "Storage",
      "scope": "storage",
      "settings": {
        "fontStyle": "",
        "foreground": "#c678dd"
      }
    },
    {
      "name": "Storage type",
      "scope": "storage.type.function",
      "settings": {
        "foreground": "#c678dd"
      }
    },
    {
      "name": "Class name",
      "scope": ["entity.name.class", "entity.name.module", "entity.name.type"],
      "settings": {
        "foreground": "#e5c07b"
      }
    },
    {
      "name": "Inherited class",
      "scope": "entity.other.inherited-class",
      "settings": {
        "foreground": "#98c379"
      }
    },
    {
      "name": "Tag name",
      "scope": "entity.name.tag",
      "settings": {
        "fontStyle": "",
        "foreground": "#e06c75"
      }
    },
    {
      "name": "Tag attribute",
      "scope": "entity.other.attribute-name",
      "settings": {
        "fontStyle": "",
        "foreground": "#d19a66"
      }
    },
    {
      "name": "Function name",
      "scope": "entity.name.function",
      "settings": {
        "fontStyle": "",
        "foreground": "#61afef"
      }
    },
    {
      "name": "Function argument",
      "scope": "variable.parameter",
      "settings": {
        "fontStyle": "italic",
        "foreground": "#e06c75"
      }
    },
    {
      "name": "Function call",
      "scope": "entity.name.function-call",
      "settings": {
        "fontStyle": "",
        "foreground": "#abb2bf"
      }
    },
    {
      "name": "Builtin Functions",
      "scope": ["function.support.builtin", "function.support.core"],
      "settings": {
        "fontStyle": "",
        "foreground": "#56b6c2"
      }
    },
    {
      "name": "Library function",
      "scope": "support.function",
      "settings": {
        "foreground": "#56b6c2"
      }
    },
    {
      "name": "Library constant",
      "scope": "support.constant",
      "settings": {
        "fontStyle": "",
        "foreground": "#e5c07b"
      }
    },
    {
      "name": "Library class/type",
      "scope": "support.class",
      "settings": {
        "foreground": "#e5c07b"
      }
    },
    {
      "name": "Library type",
      "scope": "support.type",
      "settings": {
        "foreground": "#e06c75"
      }
    },
    {
      "name": "Json Property",
      "scope": "support.dictionary.json",
      "settings": {
        "foreground": "#e06c75"
      }
    },
    {
      "name": "StyleSheet Property name",
      "scope": [
        "support.type.property-name.css",
        "support.type.property-name.scss",
        "support.type.property-name.less",
        "support.type.property-name.sass"
      ],
      "settings": {
        "foreground": "#abb2bf"
      }
    },
    {
      "name": "StyleSheet Property value",
      "scope": [
        "support.constant.css",
        "support.constant.scss",
        "support.constant.less",
        "support.constant.sass"
      ],
      "settings": {
        "foreground": "#56b6c2"
      }
    },
    {
      "name": "StyleSheet Variable",
      "scope": [
        "variable.css",
        "variable.scss",
        "variable.less",
        "variable.sass"
      ],
      "settings": {
        "foreground": "#e06c75"
      }
    },
    {
      "name": "StyleSheet Variable String",
      "scope": [
        "variable.css.string",
        "variable.scss.string",
        "variable.less.string",
        "variable.sass.string"
      ],
      "settings": {
        "foreground": "#98c379"
      }
    },
    {
      "name": "StyleSheet Unit",
      "scope": ["unit.css", "unit.scss", "unit.less", "unit.sass"],
      "settings": {
        "foreground": "#d19a66"
      }
    },
    {
      "name": "StyleSheet Function",
      "scope": [
        "function.css",
        "function.scss",
        "function.less",
        "function.sass"
      ],
      "settings": {
        "foreground": "#56b6c2"
      }
    },
    {
      "name": "Other variable",
      "scope": [
        "variable.other.property",
        "variable.other.object",
        "variable.other.block"
      ],
      "settings": {
        "foreground": "#e06c75"
      }
    },
    {
      "name": "Pug/Jade Import",
      "scope": ["jade.import.variable", "pug.import.variable"],
      "settings": {
        "foreground": "#e06c75"
      }
    },
    {
      "name": "Invalid",
      "scope": "invalid",
      "settings": {
        "background": "#c678dd",
        "fontStyle": "",
        "foreground": "#F8F8F0"
      }
    },
    {
      "name": "Invalid deprecated",
      "scope": "invalid.deprecated",
      "settings": {
        "background": "#56b6c2",
        "foreground": "#F8F8F0"
      }
    },
    {
      "name": "JSON String",
      "scope": "structure.dictionary.property-name.json",
      "settings": {
        "foreground": "#e06c75"
      }
    },
    {
      "name": "Link",
      "scope": "string.detected-link",
      "settings": {
        "foreground": "#c678dd"
      }
    },
    {
      "name": "diff.header",
      "scope": ["meta.diff", "meta.diff.header"],
      "settings": {
        "foreground": "#75715E"
      }
    },
    {
      "name": "diff.deleted",
      "scope": "markup.deleted",
      "settings": {
        "foreground": "#c678dd"
      }
    },
    {
      "name": "diff.inserted",
      "scope": "markup.inserted",
      "settings": {
        "foreground": "#e5c07b"
      }
    },
    {
      "name": "diff.changed",
      "scope": "markup.changed",
      "settings": {
        "foreground": "#98c379"
      }
    },
    {
      "scope": "constant.numeric.line-number.find-in-files - match",
      "settings": {
        "foreground": "#56b6c2A0"
      }
    },
    {
      "scope": "entity.name.filename.find-in-files",
      "settings": {
        "foreground": "#98c379"
      }
    }
  ]
}
